[
  {
    "PlayerName": "Torsten",
    "Action": "Asked for Twos"
  },
  {
    "PlayerName": "Torsten",
    "Action": "Asked for Eights"
  },
  {
    "PlayerName": "Torsten",
    "Action": "Asked for Sixs"
  },
  {
    "PlayerName": "Torsten",
    "Action": "Asked for Jacks"
  },
  {
    "PlayerName": "Torsten",
    "Action": "Asked for Tens"
  },
  {
    "PlayerName": "Torsten",
    "Action": "Asked for Eights"
  },
  {
    "PlayerName": "Torsten",
    "Action": "Asked for Tens"
  },
  {
    "PlayerName": "Torsten",
    "Action": "Asked for Nines"
  },
  {
    "PlayerName": "Torsten",
    "Action": "Asked for Tens"
  }
]